slsvd/.DS_Store
slsvd/.ipynb_checkpoints/example-checkpoint.ipynb
slsvd/__init__.py
slsvd/data_generation.py
slsvd/metrics.py
slsvd/slsvd.py
slsvd-0.1.1.dist-info/LICENSE
slsvd-0.1.1.dist-info/METADATA
slsvd-0.1.1.dist-info/WHEEL
slsvd-0.1.1.dist-info/RECORD
